systemd_watchdog/__init__.py
systemd_watchdog/py.typed
systemd_watchdog/systemd_watchdog.py
systemd_watchdog-1.0.1.dist-info/LICENSE
systemd_watchdog-1.0.1.dist-info/METADATA
systemd_watchdog-1.0.1.dist-info/WHEEL
systemd_watchdog-1.0.1.dist-info/RECORD
