Metadata-Version: 2.3
Name: systemd-watchdog
Version: 1.0.1
Summary: sd_notify and sd_watchdog_enabled functionality for writing Python daemons under systemd
License: MIT
Keywords: sd_notify,sd_watchdog_enabled,systemd,watchdog
Author: AaronDMarasco
Author-email: systemd-watchdog@marascos.net
Requires-Python: >=3.9
Classifier: Development Status :: 4 - Beta
Classifier: Intended Audience :: Developers
Classifier: License :: OSI Approved :: MIT License
Classifier: Programming Language :: Python :: 3 :: Only
Project-URL: Homepage, http://github.com/AaronDMarasco/systemd-watchdog/
Project-URL: Issues, http://github.com/AaronDMarasco/systemd-watchdog/issues
